tistorycmd/__init__.py
tistorycmd/auth.py
tistorycmd/blog.py
tistorycmd/config.py
tistorycmd/main.py
tistorycmd/server.py
tistorycmd-0.2.5.dist-info/METADATA
tistorycmd-0.2.5.dist-info/WHEEL
tistorycmd-0.2.5.dist-info/entry_points.txt
tistorycmd-0.2.5.dist-info/top_level.txt
tistorycmd-0.2.5.dist-info/RECORD
