Metadata-Version: 2.1
Name: tistorycmd
Version: 0.2.5
Summary: tistory command
Home-page: https://github.com/yy8305/py_tistory_cmd
Author: hongpark
Author-email: yy8305@naver.com
License: MIT
Platform: UNKNOWN
Classifier: Programming Language :: Python :: 3
Classifier: License :: OSI Approved :: MIT License
Classifier: Operating System :: OS Independent
Requires-Dist: pyfiglet (>=0.8)
Requires-Dist: mistune (>=0.8.4)
